README.md
setup.py
xcell/__init__.py
xcell/xcell.r
xcell.egg-info/PKG-INFO
xcell.egg-info/SOURCES.txt
xcell.egg-info/dependency_links.txt
xcell.egg-info/entry_points.txt
xcell.egg-info/requires.txt
xcell.egg-info/top_level.txt