Metadata-Version: 1.1
Name: xcell
Version: 1.1.0.1
Summary: Python CLI and module for running the xCell package with Python Pandas inputs and outputs.
Home-page: https://github.com/jason-weirather/xCell
Author: Jason L Weirather
Author-email: jason.weirather@gmail.com
License: Apache License, Version 2.0
Keywords: bioinformatics,R,enrichment,xCell,ssGSEA,microenvironment,RNAseq,immune infiltrates
Platform: UNKNOWN
Classifier: Development Status :: 3 - Alpha
Classifier: Intended Audience :: Science/Research
Classifier: Topic :: Scientific/Engineering :: Bio-Informatics
Classifier: License :: OSI Approved :: Apache Software License
